hhfetcher/__init__.py
hhfetcher/fetcher.py
hhfetcher-0.0.1.dist-info/LICENSE
hhfetcher-0.0.1.dist-info/METADATA
hhfetcher-0.0.1.dist-info/WHEEL
hhfetcher-0.0.1.dist-info/top_level.txt
hhfetcher-0.0.1.dist-info/RECORD
