Metadata-Version: 2.1
Name: hhfetcher
Version: 0.0.1
Summary: hhfetcher is used for fetching common resources in directory.
Home-page: https://github.com/shellhue/hhfetcher
Author: huangzeyu
Author-email: zeyu_huang@163.com
License: UNKNOWN
Platform: UNKNOWN
Classifier: Programming Language :: Python :: 3
Classifier: License :: OSI Approved :: MIT License
Classifier: Operating System :: OS Independent
Requires-Python: >=3.6
